baustellen_hamburg/__init__.py
baustellen_hamburg-1.0.1.dist-info/LICENSE.md
baustellen_hamburg-1.0.1.dist-info/METADATA
baustellen_hamburg-1.0.1.dist-info/WHEEL
baustellen_hamburg-1.0.1.dist-info/entry_points.txt
baustellen_hamburg-1.0.1.dist-info/top_level.txt
baustellen_hamburg-1.0.1.dist-info/RECORD
