Metadata-Version: 2.1
Name: baustellen-hamburg
Version: 1.0.1
Summary: access building sites in hamburg, germany.
Home-page: https://github.com/vigonotion/baustellen_hamburg
Author: Tom Schneider
Author-email: mail@vigonotion.com
License: MIT
Platform: UNKNOWN
Classifier: License :: OSI Approved :: Apache Software License
Classifier: Programming Language :: Python
Classifier: Programming Language :: Python :: 3
Classifier: Programming Language :: Python :: 3.6
Classifier: Programming Language :: Python :: Implementation :: CPython
Classifier: Programming Language :: Python :: Implementation :: PyPy
Requires-Python: >=3.6.0
Requires-Dist: aiohttp
Requires-Dist: python-dateutil
Requires-Dist: utm
Requires-Dist: datetime
